cal_BMI/bmi.py
cal_BMI-0.0.0.1.dist-info/METADATA
cal_BMI-0.0.0.1.dist-info/WHEEL
cal_BMI-0.0.0.1.dist-info/top_level.txt
cal_BMI-0.0.0.1.dist-info/RECORD
