Metadata-Version: 2.1
Name: cal-BMI
Version: 0.0.0.1
Summary: My BMI calculate Package
Home-page: https://blog.naver.com/rlatjf608
Author: Seol Kim
Author-email: rlatjf60854@gmail.com
License: MIT
Platform: UNKNOWN
Requires-Python: >=3
